browsy/__init__.py
browsy/__main__.py
browsy/_client.py
browsy/_database.py
browsy/_jobs.py
browsy/_models.py
browsy/_server.py
browsy/_worker.py
browsy/templates/base.html
browsy/templates/jobs.html
browsy/templates/workers.html
browsy-0.0.8.dist-info/METADATA
browsy-0.0.8.dist-info/WHEEL
browsy-0.0.8.dist-info/entry_points.txt
browsy-0.0.8.dist-info/licenses/LICENSE
browsy-0.0.8.dist-info/RECORD
