Metadata-Version: 2.4
Name: browsy
Version: 0.0.8
Summary: Playwright-based browser automation service with HTTP API and Docker support
Author-email: Michal Broton <michal@broton.dev>
License-File: LICENSE
Keywords: automation,browser,docker,pdf,playwright,queue,scraping,screenshot
Classifier: Development Status :: 4 - Beta
Classifier: Environment :: Web Environment
Classifier: Framework :: FastAPI
Classifier: Intended Audience :: Developers
Classifier: License :: OSI Approved :: MIT License
Classifier: Operating System :: OS Independent
Classifier: Programming Language :: Python :: 3
Classifier: Programming Language :: Python :: 3.9
Classifier: Programming Language :: Python :: 3.10
Classifier: Programming Language :: Python :: 3.11
Classifier: Programming Language :: Python :: 3.12
Classifier: Programming Language :: Python :: 3.13
Classifier: Topic :: Internet :: WWW/HTTP
Classifier: Topic :: Software Development :: Libraries :: Python Modules
Classifier: Topic :: Software Development :: Testing
Requires-Python: >=3.9
Requires-Dist: click>=8.1.7
Requires-Dist: httpx>=0.28.1
Requires-Dist: playwright>=1.49.1
Requires-Dist: pydantic>=1.7.4
Requires-Dist: requests>=2.32.3
Provides-Extra: all
Requires-Dist: aiosqlite>=0.20.0; extra == 'all'
Requires-Dist: fastapi>=0.115.6; extra == 'all'
Requires-Dist: jinja2>=3.1.5; extra == 'all'
Requires-Dist: uvicorn>=0.34.0; extra == 'all'
Provides-Extra: server
Requires-Dist: aiosqlite>=0.20.0; extra == 'server'
Requires-Dist: fastapi>=0.115.6; extra == 'server'
Requires-Dist: jinja2>=3.1.5; extra == 'server'
Requires-Dist: uvicorn>=0.34.0; extra == 'server'
Provides-Extra: worker
Requires-Dist: aiosqlite>=0.20.0; extra == 'worker'
